{"bll": [["28th-Marc-1952", 37, 14], ["30th-January-1973", 31, 7], ["30th-June-1987", 59, 10], ["28th-June-1968", 69, 8], ["28th-June-1968", 50, 25], ["5th-December-1975", 24, 22], ["5th-April-1976", 44, 19], ["10th-April-1964", 64, 22], ["2nd-Augus-1973", 60, 0], ["26th-February-1949", 33, 12], ["1st-October-1985", 268, 0], ["12th-Marc-1948", 8, 13], ["3rd-January-1973", 72, 30], ["21st-Augus-1972", 25, 0], ["31st-July-1965", 23, 10]], "blledxxh": [["20th-September-1987", 35, 43]], "bllut": [["27th-November-1973", 36, 10]], "bllistic": [["18th-December-1995", 61, 3]], "blll": [["13th-February-1992", 92, 0], ["5th-Augus-1964", 68, 10]], "bllahi": [["30th-July-2004", 67, 25], ["27th-Marc-1977", 1, 5]]}