{"cpsp": [["15th-December-2005", 64, 6], ["21st-June-2022", 12, 0], ["16th-February-2006", 10, 2], ["16th-February-2006", 10, 3], ["16th-February-2006", 10, 13], ["16th-February-2006", 10, 25], ["16th-February-2006", 10, 35], ["16th-February-2006", 11, 7], ["16th-February-2006", 11, 25], ["16th-February-2006", 7, 5], ["16th-February-2006", 7, 7], ["16th-February-2006", 7, 8], ["17th-June-2004", 92, 11], ["8th-June-2022", 33, 0], ["2nd-September-2005", 31, 1], ["2nd-September-2005", 31, 4], ["2nd-September-2005", 30, 17], ["2nd-September-2005", 30, 19]], "cpsc": [["24th-November-1966", 20, 2], ["24th-November-1966", 20, 48], ["24th-November-1966", 19, 24], ["16th-June-1967", 5, 4], ["16th-June-1967", 6, 2], ["30th-Marc-1963", 72, 17], ["7th-December-1968", 27, 2], ["7th-December-1968", 27, 5], ["25th-May-1967", 20, 21], ["12th-December-1966", 15, 49], ["12th-December-1966", 15, 71], ["12th-December-1966", 14, 112], ["12th-December-1966", 9, 7], ["12th-December-1966", 9, 53], ["12th-December-1966", 8, 74], ["12th-December-1966", 8, 154], ["12th-December-1966", 2, 27], ["28th-November-1966", 21, 19], ["28th-November-1966", 21, 20], ["14th-September-1972", 34, 23], ["5th-December-1966", 28, 27], ["5th-December-1966", 28, 28], ["29th-November-1965", 8, 11], ["29th-November-1965", 6, 7], ["29th-November-1965", 3, 10], ["29th-November-1965", 3, 11], ["29th-November-1965", 3, 12], ["7th-December-1966", 8, 4], ["7th-June-1967", 20, 47], ["7th-June-1967", 26, 30], ["4th-Augus-1973", 7, 2], ["3rd-June-1968", 17, 10], ["13th-June-1968", 26, 1], ["13th-June-1968", 25, 30], ["16th-June-1966", 43, 31], ["5th-June-1968", 27, 43], ["5th-June-1968", 31, 30], ["5th-June-1968", 24, 42], ["5th-June-1968", 30, 11], ["13th-April-1964", 5, 2], ["13th-April-1964", 1, 19], ["23rd-December-1966", 5, 0], ["27th-May-1968", 5, 7], ["27th-July-1965", 6, 9], ["27th-July-1965", 6, 10], ["27th-July-1965", 6, 12], ["27th-July-1965", 6, 14], ["27th-July-1965", 7, 7], ["26th-July-1965", 6, 56], ["22nd-November-1965", 5, 4], ["22nd-November-1965", 5, 7], ["22nd-November-1965", 4, 26], ["18th-January-1965", 10, 36], ["18th-January-1965", 10, 53], ["18th-January-1965", 51, 14], ["18th-January-1965", 51, 19], ["18th-January-1965", 50, 19], ["18th-January-1965", 50, 21], ["18th-January-1965", 50, 22], ["18th-January-1965", 50, 38], ["18th-January-1965", 50, 49], ["18th-November-1965", 10, 17], ["27th-January-1969", 16, 67], ["23rd-June-1967", 64, 22], ["12th-June-1968", 8, 13], ["12th-June-1968", 5, 9], ["12th-June-1968", 5, 13], ["12th-June-1968", 5, 22], ["12th-June-1968", 6, 6], ["12th-June-1968", 25, 9], ["12th-June-1968", 25, 13], ["7th-February-1969", 29, 2], ["23rd-July-1965", 11, 5], ["23rd-July-1965", 11, 6], ["23rd-July-1965", 11, 7], ["23rd-July-1965", 11, 8], ["23rd-July-1965", 11, 9], ["9th-Marc-1963", 36, 22], ["6th-June-1966", 31, 12], ["31st-January-1973", 61, 11], ["31st-January-1973", 61, 33], ["31st-January-1973", 60, 39], ["31st-January-1973", 65, 7], ["2nd-April-1964", 14, 11], ["13th-December-1967", 1, 26], ["23rd-June-1966", 25, 13], ["23rd-June-1966", 25, 14], ["23rd-June-1966", 25, 21], ["17th-December-1968", 14, 11], ["30th-November-1966", 6, 8], ["30th-November-1966", 1, 10], ["26th-June-1968", 17, 4], ["26th-June-1968", 18, 2], ["26th-June-1968", 18, 6], ["26th-June-1968", 18, 9], ["26th-June-1968", 18, 20], ["26th-June-1968", 18, 27], ["28th-June-1965", 13, 1], ["28th-June-1965", 13, 5], ["28th-June-1965", 12, 19], ["28th-June-1965", 12, 27], ["13th-December-1968", 13, 14], ["13th-December-1968", 10, 35]], "cpscnomine": [["17th-Marc-1966", 10, 17], ["17th-Marc-1966", 10, 23]], "cps7": [["19th-June-2006", 40, 0], ["19th-June-2006", 40, 6]], "cps1": [["19th-June-2006", 40, 0], ["19th-June-2006", 40, 1]], "cps10": [["19th-June-2006", 40, 0], ["19th-June-2006", 40, 7]], "cps4": [["19th-June-2006", 40, 0], ["19th-June-2006", 40, 6], ["19th-June-2006", 40, 7]], "cps8": [["19th-June-2006", 40, 0], ["19th-June-2006", 40, 7]], "cps11": [["19th-June-2006", 40, 0], ["19th-June-2006", 40, 7]], "cps9": [["19th-June-2006", 40, 0]], "cps12": [["19th-June-2006", 40, 0], ["19th-June-2006", 40, 7]], "cps6": [["19th-June-2006", 40, 0], ["19th-June-2006", 40, 6]], "cps5": [["19th-June-2006", 40, 0]], "cps2": [["19th-June-2006", 40, 0], ["19th-June-2006", 40, 6]], "cps3": [["19th-June-2006", 40, 6]], "cpss": [["19th-June-2006", 40, 6], ["5th-November-1985", 13, 35]], "cpscqualifi": [["1st-July-1968", 10, 7], ["1st-July-1968", 10, 13]], "cpsu": [["20th-April-1988", 3, 11]], "cpscand": [["30th-November-1966", 6, 1]], "cpscestt": [["26th-June-1968", 18, 7]], "cpscc": [["24th-January-1996", 45, 35]]}