{"enna": [["8th-October-1987", 32, 58], ["8th-June-1973", 46, 22], ["24th-Marc-2016", 66, 0]], "enn": [["9th-December-1966", 40, 22], ["4th-April-1963", 71, 31], ["8th-June-1973", 46, 23], ["14th-April-1964", 30, 26], ["5th-June-1967", 68, 37], ["17th-January-1988", 45, 14], ["17th-December-1995", 157, 2], ["17th-April-1994", 54, 79], ["17th-April-1994", 53, 96], ["19th-May-1967", 15, 15], ["18th-June-1975", 121, 10], ["29th-Marc-1954", 32, 18], ["21st-Augus-1997", 61, 30], ["5th-February-1974", 11, 13], ["16th-June-1976", 84, 17]], "ennobl": [["17th-Marc-1966", 60, 15], ["28th-June-1968", 33, 35], ["7th-April-1951", 56, 5], ["1st-February-1956", 33, 14], ["8th-Marc-1958", 60, 19], ["29th-February-1956", 76, 10], ["29th-September-1955", 37, 18], ["19th-September-2014", 48, 4], ["21st-February-1956", 49, 25]], "ennd": [["8th-June-1973", 45, 25]], "enno": [["7th-April-2010", 69, 0]], "enng": [["7th-May-1991", 42, 6], ["7th-May-1991", 42, 38], ["7th-May-1991", 42, 82]], "ennen": [["29th-June-1968", 21, 4], ["29th-November-1973", 9, 0], ["3rd-May-1992", 70, 0]], "ennedifi": [["19th-June-2006", 146, 0]], "enner": [["31st-January-1974", 35, 10], ["17th-December-1988", 125, 0]], "ennuiti": [["21st-April-1987", 102, 1]], "ennil": [["23rd-June-1976", 17, 2]], "ennival": [["15th-September-1972", 38, 3]], "enndit": [["21st-June-1968", 53, 22]], "ennnot": [["15th-June-1968", 104, 13]], "ennounc": [["7th-June-1967", 2, 33], ["17th-October-2003", 15, 3], ["21st-February-2007", 115, 0]], "ennamalqqu": [["5th-December-1973", 3, 1]], "ennes": [["9th-Marc-2005", 129, 1]], "ennomi": [["30th-May-1992", 62, 0], ["10th-Marc-1998", 26, 0], ["6th-December-1989", 47, 7]], "ennironment": [["11th-November-1986", 11, 6]], "ennsult": [["5th-June-1967", 53, 6]], "ennial": [["22nd-June-1964", 23, 13], ["23rd-June-1973", 17, 1]], "ennot": [["30th-May-1967", 56, 6]], "ennu": [["17th-April-1994", 53, 96]], "ennanc": [["13th-Marc-1987", 4, 6], ["10th-Marc-1958", 23, 7]], "ennay": [["18th-June-1986", 10, 8]], "ennual": [["9th-April-1964", 76, 26]], "ennz": [["19th-Marc-2004", 106, 2]], "ennecllod": [["18th-May-1948", 12, 23]], "ennet": [["22nd-June-2019", 90, 2], ["23rd-October-1953", 17, 5]], "ennah": [["16th-November-2002", 11, 2]], "enni": [["10th-December-1989", 21, 1], ["1st-June-2004", 28, 0], ["25th-November-1997", 20, 6], ["19th-November-1952", 15, 10], ["19th-November-1952", 15, 20], ["10th-October-1950", 23, 12], ["10th-October-1950", 23, 14], ["8th-October-1985", 54, 6], ["31st-December-1989", 14, 0]], "ennahad": [["14th-June-2003", 178, 24]], "enniest": [["14th-Marc-1986", 66, 0]], "ennsur": [["21st-December-2011", 45, 0], ["2nd-October-2018", 21, 0]], "ennshrin": [["14th-April-2009", 26, 0]], "ennon": [["15th-December-1976", 135, 1]], "ennal": [["12th-June-2007", 35, 10], ["11th-October-1987", 48, 5]]}