{"erglish": [["16th-June-1967", 46, 78], ["2nd-July-1962", 13, 51], ["1st-June-1967", 65, 40], ["6th-June-1966", 54, 47], ["19th-November-1965", 87, 34], ["28th-Marc-1964", 14, 41], ["6th-April-1963", 40, 32]], "erguay": [["10th-May-1992", 49, 220]], "ergenc": [["15th-Marc-1966", 68, 15], ["4th-Marc-1974", 80, 8], ["3rd-Marc-1974", 41, 5], ["11th-October-1950", 118, 44], ["20th-July-1965", 43, 41], ["21st-December-1966", 43, 0], ["29th-Marc-1956", 52, 11]], "erg": [["11th-June-1999", 49, 16], ["25th-Marc-1950", 38, 9], ["26th-February-1998", 55, 42], ["29th-October-1997", 55, 1]], "ergish": [["27th-November-1965", 33, 35]], "ergland": [["19th-June-1975", 74, 1], ["7th-Marc-1973", 46, 33]], "ergotamin": [["13th-September-1972", 18, 16], ["25th-June-1974", 10, 2]], "ergometrin": [["13th-September-1972", 18, 17], ["25th-June-1974", 10, 2], ["29th-October-1997", 58, 9]], "ergot": [["29th-Marc-1952", 11, 17], ["23rd-September-2004", 51, 6]], "ergo": [["12th-June-1974", 62, 1], ["8th-February-1993", 106, 6]], "erghth": [["7th-October-1985", 153, 0]], "ergashov": [["13th-May-2005", 34, 12]], "ergotoxin": [["25th-June-1974", 10, 2]], "ergetur": [["7th-December-1973", 40, 0]], "ergarten": [["1st-February-1956", 22, 13]], "ergi": [["23rd-June-1973", 32, 0]], "ergonom": [["16th-June-2004", 60, 8]], "erglab": [["8th-June-1967", 70, 51]], "erget": [["17th-May-1948", 17, 5]], "ergan": [["14th-June-1974", 9, 1]], "ergratin": [["18th-February-1993", 66, 3]]}