{"eunuch": [["15th-September-2020", 89, 0], ["15th-September-2020", 8, 0], ["8th-November-2019", 55, 3], ["22nd-April-1974", 65, 11], ["9th-Marc-2020", 86, 2], ["28th-June-1968", 70, 12], ["27th-June-1973", 37, 12], ["18th-January-2019", 73, 5], ["19th-November-2002", 15, 6], ["29th-December-2011", 15, 3], ["14th-June-2005", 186, 0], ["15th-Marc-2010", 71, 20], ["15th-Marc-2010", 73, 1], ["15th-Marc-2010", 73, 2], ["15th-Marc-2010", 72, 0], ["15th-Marc-2010", 72, 13], ["8th-January-2020", 9, 7], ["12th-June-2006", 204, 1], ["7th-February-2013", 26, 1], ["7th-February-2013", 27, 0], ["14th-June-2007", 134, 0], ["13th-November-2012", 10, 1], ["13th-November-2012", 11, 4], ["13th-November-2012", 11, 14], ["13th-November-2012", 9, 7]], "eunu": [["24th-October-1991", 32, 3], ["20th-June-1967", 15, 37], ["20th-June-1967", 14, 19], ["20th-June-1967", 13, 50], ["3rd-Marc-2003", 147, 0], ["26th-Augus-1957", 14, 16]], "eungw": [["13th-September-2019", 65, 3]], "eunhama": [["17th-Marc-1999", 82, 3]], "eunt": [["5th-September-1996", 112, 1], ["4th-December-1985", 24, 1]], "eund": [["6th-June-1973", 4, 27]], "eun": [["18th-June-1976", 31, 1], ["9th-February-1993", 41, 7], ["9th-September-1992", 59, 1], ["9th-September-1992", 3, 16], ["17th-April-1994", 54, 43], ["17th-April-1994", 53, 96], ["16th-Augus-1992", 26, 1], ["12th-Augus-1992", 63, 0], ["12th-Augus-1992", 87, 0], ["17th-Augus-1992", 58, 23], ["3rd-September-1998", 33, 1]], "euni": [["30th-September-1987", 37, 0]], "euneer": [["15th-February-1987", 87, 3]], "eunn": [["17th-April-1994", 53, 96]], "eunuoo": [["7th-December-1973", 13, 15]], "euno": [["14th-June-1990", 65, 0]], "eunquir": [["31st-Marc-1997", 93, 5]], "eunuchi": [["9th-December-1985", 112, 0]], "eunesday": [["4th-February-1987", 1, 1]], "euntaril": [["20th-December-1973", 43, 11]], "eunnlag": [["26th-May-1997", 97, 8]], "eunner": [["9th-Marc-1998", 20, 0]], "eunct": [["3rd-July-1967", 77, 1]]}