{"exnaut": [["7th-February-2007", 56, 13]], "exnaib": [["7th-February-2007", 56, 58], ["19th-April-1995", 71, 4], ["19th-April-1995", 71, 23], ["19th-April-1995", 72, 21], ["19th-April-1995", 72, 31], ["19th-April-1995", 72, 52]], "exnfc": [["28th-Augus-1996", 85, 58]], "exnect": [["17th-June-1974", 60, 9]], "exnight": [["17th-Marc-1966", 13, 37]], "exnara": [["4th-November-1953", 60, 19]], "exnasrat": [["4th-November-1953", 60, 22]], "exnawab": [["13th-Marc-1963", 20, 16], ["13th-Marc-1963", 20, 21], ["25th-June-1965", 39, 3], ["6th-July-1962", 9, 25], ["22nd-January-2010", 76, 0], ["22nd-January-2010", 75, 9]], "exn": [["21st-June-2008", 291, 1], ["25th-February-1992", 76, 3], ["23rd-September-1998", 53, 1], ["6th-April-1956", 32, 11], ["28th-July-1965", 24, 26], ["9th-May-1991", 78, 4], ["22nd-May-1968", 46, 6], ["11th-June-1991", 22, 68], ["10th-Marc-1948", 46, 12], ["29th-July-2013", 35, 0], ["27th-November-1997", 79, 5]], "exnlain": [["26th-November-1966", 78, 46]], "exnai": [["26th-June-1990", 10, 21]], "exnrsteach": [["26th-June-1990", 75, 0]], "exnr": [["26th-June-1990", 74, 20], ["19th-February-1991", 82, 2]], "exnetcom": [["31st-Marc-1996", 92, 1], ["31st-Marc-1996", 92, 3], ["4th-June-1995", 34, 5], ["4th-June-1995", 37, 0], ["4th-June-1995", 37, 2]], "exnrsp": [["7th-June-1993", 47, 4], ["4th-Augus-1992", 78, 12]], "exnam": [["9th-April-2022", 60, 8], ["9th-April-2022", 60, 10], ["19th-January-2022", 7, 0], ["25th-November-2022", 56, 2], ["25th-November-2022", 56, 11], ["25th-November-2022", 46, 12], ["3rd-April-2022", 60, 8], ["3rd-April-2022", 60, 10]], "exnorth": [["27th-September-2010", 53, 2], ["11th-June-2003", 94, 17], ["11th-June-2003", 95, 0]], "exnat": [["19th-Marc-2010", 75, 16], ["5th-December-1997", 24, 29], ["5th-December-1997", 24, 36]], "exnewst": [["28th-June-1995", 94, 0]], "exnav": [["5th-February-1969", 37, 7], ["5th-February-1969", 37, 15], ["30th-November-1966", 35, 17]], "exnotic": [["27th-January-1973", 66, 11]], "exniampl": [["7th-December-1989", 56, 3]], "exnort": [["14th-June-1973", 24, 21]], "exnendi": [["5th-December-1967", 54, 28]], "exnor": [["22nd-June-1968", 99, 39]], "exnder": [["7th-February-1993", 75, 10]], "exnsa": [["24th-June-2019", 127, 0]], "exnaveel": [["10th-September-2014", 16, 0]]}