{"hoy": [["10th-December-1973", 29, 12], ["13th-December-1966", 71, 25], ["19th-July-2004", 30, 26], ["15th-Marc-1954", 17, 8], ["12th-June-1987", 7, 11], ["29th-Marc-1952", 43, 23], ["21st-Augus-1996", 51, 8], ["12th-June-1974", 70, 38], ["27th-June-1995", 92, 3], ["7th-December-1973", 23, 23], ["13th-July-1972", 39, 28], ["25th-June-1989", 50, 0], ["6th-May-1976", 67, 4], ["10th-Augus-2021", 11, 0], ["28th-Marc-2022", 61, 2], ["9th-February-1992", 20, 7], ["21st-Augus-1976", 19, 1], ["4th-December-1973", 38, 6], ["28th-November-1973", 72, 6]], "hoyler": [["8th-June-1973", 50, 26]], "hoycol": [["3rd-May-2005", 6, 0]], "hoycolt": [["3rd-May-2005", 6, 0]], "hoyi": [["13th-June-2007", 241, 0], ["12th-June-2015", 95, 0]], "hoycot": [["26th-January-1986", 100, 1], ["26th-June-1994", 111, 5]], "hoyli": [["26th-January-1986", 1, 2]], "hoyechay": [["4th-Marc-1958", 30, 32]], "hoya": [["30th-September-1955", 46, 52], ["17th-June-1995", 44, 9]]}