{"jhoka": [["23rd-June-1997", 61, 52], ["20th-Augus-1997", 25, 3], ["20th-Augus-1997", 25, 30]], "jhoke": [["21st-April-2003", 41, 7], ["25th-Augus-1996", 18, 14], ["10th-October-1989", 58, 6], ["9th-October-1996", 10, 18], ["1st-February-1987", 30, 33], ["4th-Augus-2006", 41, 2], ["11th-April-1996", 29, 1], ["11th-April-1996", 29, 4], ["30th-June-1997", 16, 8], ["2nd-September-1996", 4, 20], ["6th-June-1989", 95, 25], ["23rd-April-1987", 40, 17], ["23rd-January-1994", 50, 27], ["4th-Marc-1998", 6, 2], ["12th-June-1994", 75, 15], ["3rd-December-1989", 58, 48], ["18th-December-1995", 37, 7], ["15th-May-1996", 56, 19], ["31st-May-1973", 27, 21], ["21st-Augus-2008", 92, 7], ["21st-Augus-2008", 92, 9], ["23rd-February-2005", 73, 3], ["26th-July-2004", 93, 1]], "jhodo": [["15th-September-2020", 20, 0], ["9th-May-2018", 113, 0]], "jhoomar": [["28th-November-1975", 21, 28]], "jhonkai": [["6th-September-2005", 7, 4]], "jhopri": [["1st-April-1952", 36, 4]], "jhol": [["14th-September-1989", 5, 27], ["27th-January-1999", 40, 2], ["18th-June-1995", 41, 4], ["5th-December-1962", 7, 14], ["17th-December-1995", 82, 8], ["25th-Augus-1997", 106, 9], ["26th-June-1989", 14, 45], ["12th-June-1989", 13, 0], ["4th-April-1991", 35, 5], ["28th-June-1962", 2, 1], ["28th-June-1962", 1, 30], ["28th-June-1962", 1, 32], ["1st-April-2004", 50, 2], ["1st-April-2004", 50, 5], ["1st-April-2004", 50, 7], ["1st-April-2004", 50, 8], ["26th-June-1996", 27, 23]], "jhok": [["3rd-June-1986", 49, 18], ["11th-June-1987", 49, 4], ["9th-July-1973", 7, 6], ["5th-October-1989", 14, 35]], "jhonpari": [["3rd-June-1986", 99, 3], ["22nd-June-1994", 178, 1]], "jhoot": [["22nd-June-1994", 198, 1], ["21st-September-1995", 26, 9], ["13th-June-1968", 12, 14], ["15th-September-1996", 47, 5], ["27th-April-2009", 77, 2], ["22nd-June-1968", 55, 34], ["12th-December-1994", 42, 3], ["10th-February-1992", 93, 12]], "jhon": [["19th-Marc-2003", 80, 0], ["19th-June-1968", 38, 35], ["6th-Marc-1988", 71, 4], ["2nd-September-1997", 15, 8], ["27th-Augus-1997", 34, 3], ["23rd-June-1996", 58, 10], ["29th-May-1994", 76, 1], ["7th-April-1964", 23, 32], ["23rd-November-1976", 40, 37], ["23rd-November-1976", 41, 2], ["23rd-November-1976", 41, 10], ["23rd-November-1976", 41, 26], ["14th-July-1972", 73, 40], ["29th-May-1990", 79, 91], ["29th-May-1990", 79, 94], ["29th-October-1997", 38, 13], ["1st-October-1998", 112, 11]], "jhokditta": [["27th-January-1999", 41, 28]], "jhong": [["5th-September-1996", 59, 49], ["21st-December-1995", 29, 54], ["26th-June-1994", 6, 31]], "jhoom": [["15th-Marc-2018", 73, 19]], "jhone": [["25th-February-1998", 7, 72]], "jhonson": [["31st-January-1974", 21, 55], ["14th-February-1974", 147, 16], ["29th-May-1990", 77, 8], ["3rd-Marc-1958", 51, 53]], "jhoni": [["16th-September-1955", 11, 7], ["16th-September-1955", 11, 13]], "jhonidha": [["25th-June-1966", 13, 19]], "jhora": [["15th-June-1966", 14, 29], ["15th-June-1966", 14, 32], ["15th-June-1966", 14, 33]], "jhoug": [["3rd-June-1991", 46, 9]], "jhokhan": [["14th-June-2006", 152, 0]], "jhonpra": [["24th-January-1994", 170, 4], ["14th-June-1975", 39, 24]], "jhokan": [["17th-December-2018", 77, 14], ["17th-December-2018", 73, 9]], "jhogi": [["14th-January-2016", 32, 0]], "jhoungra": [["24th-Augus-2006", 62, 6]], "jhoomer": [["6th-December-1973", 64, 12]], "jhotial": [["4th-September-1994", 54, 24]], "jhoo": [["12th-Marc-2004", 128, 10]], "jhonni": [["4th-September-1958", 26, 18]], "jholpur": [["3rd-December-1989", 78, 37]], "jhole": [["20th-May-1990", 57, 19], ["23rd-February-2005", 124, 95]], "jhonsti": [["7th-July-1966", 52, 29]], "jhoongal": [["20th-Augus-2008", 73, 34]], "jhol1": [["19th-February-1991", 47, 8]], "jhola": [["25th-June-1987", 25, 7]], "jhoder": [["18th-June-1990", 88, 60]], "jhoko": [["29th-June-1963", 24, 0]]}