{"lii": [["11th-December-1973", 32, 17], ["17th-May-1992", 16, 2], ["18th-January-1995", 72, 10], ["17th-Marc-1966", 17, 55], ["17th-Marc-1966", 49, 33], ["17th-Marc-1966", 65, 47], ["17th-Marc-1966", 69, 22], ["17th-Marc-1966", 1, 26], ["17th-Marc-1966", 33, 28], ["25th-November-1965", 54, 1], ["25th-November-1965", 52, 1], ["25th-November-1965", 52, 3], ["25th-November-1965", 52, 5], ["17th-June-1963", 1, 26], ["21st-June-2006", 155, 0], ["15th-Marc-1966", 17, 50], ["15th-Marc-1966", 89, 36], ["15th-Marc-1966", 49, 53], ["15th-Marc-1966", 65, 35], ["15th-Marc-1966", 81, 27], ["15th-Marc-1966", 1, 29], ["15th-Marc-1966", 33, 39], ["4th-April-1963", 49, 48], ["4th-April-1963", 65, 37], ["4th-April-1963", 73, 44], ["7th-June-1994", 20, 5], ["30th-May-1963", 17, 40], ["30th-May-1963", 51, 19], ["30th-May-1963", 1, 19], ["11th-June-1963", 67, 30], ["11th-June-1963", 43, 32], ["26th-October-2020", 42, 2], ["7th-January-1977", 83, 12], ["7th-January-1977", 83, 14], ["7th-January-1977", 83, 18], ["21st-November-2008", 73, 10], ["18th-July-1974", 15, 51], ["21st-Marc-1963", 17, 35], ["21st-Marc-1963", 63, 34], ["21st-Marc-1963", 95, 37], ["21st-Marc-1963", 79, 35], ["21st-Marc-1963", 1, 29], ["21st-Marc-1963", 19, 37], ["7th-December-1985", 161, 11], ["6th-Augus-1963", 17, 54], ["6th-Augus-1963", 49, 26], ["6th-Augus-1963", 1, 26], ["6th-Augus-1963", 33, 44], ["25th-July-1963", 17, 35], ["25th-July-1963", 1, 35], ["25th-July-1963", 33, 23], ["10th-December-1995", 16, 65], ["27th-Marc-1963", 49, 35], ["27th-Marc-1963", 33, 40], ["21st-Marc-1966", 17, 33], ["21st-Marc-1966", 49, 36], ["21st-Marc-1966", 65, 36], ["21st-Marc-1966", 33, 51], ["18th-Marc-1963", 17, 29], ["12th-May-1996", 136, 18], ["18th-June-1963", 17, 50], ["18th-June-1963", 49, 82], ["18th-June-1963", 1, 33], ["4th-December-1963", 1, 36], ["4th-December-1963", 33, 43], ["13th-April-1964", 49, 37], ["13th-April-1964", 81, 38], ["21st-June-1995", 93, 13], ["14th-October-2009", 88, 5], ["22nd-December-1963", 17, 95], ["1st-April-1963", 49, 36], ["1st-April-1963", 33, 24], ["13th-October-2009", 20, 11], ["13th-October-2009", 19, 13], ["13th-October-2009", 18, 7], ["3rd-December-1973", 11, 1], ["29th-Marc-1963", 17, 73], ["29th-Marc-1963", 54, 16], ["29th-Marc-1963", 33, 41], ["15th-November-1965", 24, 31], ["5th-December-1963", 17, 58], ["12th-February-1989", 37, 142], ["9th-Marc-1998", 44, 21], ["9th-Marc-1998", 46, 19], ["30th-December-1972", 63, 16], ["13th-July-1965", 30, 22], ["19th-Marc-1963", 17, 31], ["22nd-Marc-1966", 17, 56], ["22nd-Marc-1966", 49, 28], ["22nd-Marc-1966", 65, 29], ["22nd-Marc-1966", 1, 80], ["22nd-Marc-1966", 33, 52], ["19th-April-1963", 49, 47], ["26th-July-1963", 1, 14], ["26th-July-1963", 33, 46], ["19th-June-1963", 17, 38], ["19th-June-1963", 49, 39], ["19th-June-1963", 65, 52], ["19th-June-1963", 81, 42], ["19th-June-1963", 97, 31], ["18th-May-2018", 29, 1], ["18th-May-2018", 40, 0], ["18th-May-2018", 41, 3], ["18th-May-2018", 37, 5], ["6th-November-1997", 186, 7]], "liii": [["18th-January-1995", 72, 12], ["25th-February-1998", 82, 4], ["7th-May-2007", 15, 13], ["15th-Marc-2016", 20, 2], ["15th-Marc-2016", 25, 4], ["17th-November-1997", 36, 7], ["12th-May-1996", 136, 21], ["31st-October-2018", 69, 13], ["31st-October-2018", 24, 1], ["14th-October-2009", 88, 8], ["7th-November-2007", 25, 1], ["8th-January-2020", 79, 4], ["9th-Marc-1998", 44, 23], ["9th-Marc-1998", 46, 21], ["30th-December-1972", 63, 18], ["20th-Augus-1996", 51, 3], ["20th-Augus-1996", 51, 11], ["7th-Marc-1966", 60, 22], ["21st-February-2019", 46, 5], ["21st-February-2019", 30, 4], ["19th-January-2009", 63, 8], ["18th-May-2018", 29, 1], ["18th-May-2018", 38, 0], ["18th-May-2018", 40, 0], ["18th-May-2018", 41, 3]], "lii58": [["17th-June-1963", 17, 38]], "lii39": [["30th-May-1963", 49, 36]], "liinist": [["11th-Marc-1966", 13, 0]], "liimself": [["28th-October-1991", 99, 28]], "liiv1417": [["4th-September-1997", 18, 1]], "liiw": [["4th-June-2008", 4, 5], ["30th-June-1973", 72, 31]], "liita": [["7th-December-1973", 19, 12]], "liivestock": [["14th-June-2006", 221, 0]], "lii8": [["3rd-December-1973", 45, 6]], "lii1127": [["5th-Augus-1963", 33, 41]], "liidu": [["28th-April-1994", 49, 22]], "liion": [["25th-June-1987", 12, 0]], "liia": [["6th-May-1991", 37, 11]], "liin": [["22nd-October-2004", 19, 1]], "liiri": [["29th-June-1999", 31, 0]], "liiialkhidmat": [["18th-May-2018", 41, 3]], "liilur": [["19th-June-1990", 21, 22]]}