{"mpeaa": [["26th-June-1974", 21, 15], ["26th-June-1974", 21, 16], ["20th-February-1986", 10, 6], ["28th-September-1989", 55, 4]], "mpete": [["26th-June-1990", 99, 0]], "mpeon": [["25th-April-2019", 34, 15], ["25th-April-2019", 33, 16], ["25th-April-2019", 33, 30], ["25th-April-2019", 33, 34], ["25th-April-2019", 33, 38], ["6th-May-2019", 76, 5], ["6th-May-2019", 76, 11], ["6th-May-2019", 76, 13], ["6th-May-2019", 76, 23], ["6th-May-2019", 76, 29], ["6th-May-2019", 76, 52], ["31st-May-2004", 108, 20], ["31st-May-2004", 108, 21], ["31st-May-2004", 108, 25], ["31st-May-2004", 108, 26], ["31st-May-2004", 108, 28], ["31st-May-2004", 108, 31], ["31st-May-2004", 108, 32], ["31st-May-2004", 108, 33]], "mpesin": [["19th-February-1992", 21, 5]], "mpeaker": [["26th-Augus-1976", 1, 5], ["9th-July-1986", 68, 8]], "mpea": [["31st-May-2004", 108, 19]], "mpensat": [["4th-February-1975", 40, 5]], "mpe": [["5th-April-1952", 49, 25]]}