{"ncourag": [["20th-June-2008", 307, 0]], "nco": [["23rd-June-1997", 7, 26], ["29th-June-2020", 10, 0], ["7th-June-1975", 16, 46], ["7th-June-1975", 16, 51], ["7th-June-1975", 16, 53], ["7th-June-1975", 16, 63], ["11th-June-1999", 7, 3], ["17th-September-2013", 49, 0], ["21st-Marc-1966", 61, 7], ["21st-Marc-1966", 61, 17], ["21st-Marc-1966", 61, 52], ["10th-June-1975", 8, 10], ["14th-February-1993", 131, 4], ["8th-September-2003", 12, 31], ["8th-September-2003", 12, 36], ["30th-May-1967", 37, 13], ["30th-May-1967", 31, 5], ["30th-May-1967", 31, 6], ["30th-May-1967", 31, 10], ["30th-May-1967", 31, 11], ["16th-June-1966", 13, 34], ["27th-January-2006", 51, 17], ["27th-January-2006", 51, 19], ["27th-January-2006", 52, 3], ["27th-January-2006", 52, 5], ["27th-January-2006", 52, 8], ["19th-Marc-2004", 90, 0], ["16th-June-1994", 93, 1], ["25th-February-2013", 44, 0], ["17th-April-1964", 12, 1], ["17th-April-1964", 11, 20], ["17th-April-1964", 11, 22], ["12th-Augus-1985", 4, 1], ["7th-June-2004", 100, 2], ["21st-April-2008", 40, 12], ["24th-June-2021", 48, 0], ["23rd-November-1965", 74, 5], ["22nd-January-2009", 90, 14], ["2nd-June-1986", 33, 13], ["2nd-June-1986", 33, 15], ["2nd-June-1986", 33, 17], ["22nd-June-2020", 98, 0], ["3rd-July-1962", 13, 4]], "ncoc": [["10th-June-2020", 93, 0], ["10th-June-2020", 76, 0], ["10th-June-2020", 58, 0], ["10th-June-2020", 95, 0], ["15th-September-2020", 90, 0], ["15th-September-2020", 37, 0], ["15th-September-2020", 36, 1], ["23rd-June-2020", 53, 1], ["23rd-June-2020", 119, 0], ["1st-April-2021", 49, 2], ["1st-April-2021", 49, 3], ["1st-April-2021", 49, 4], ["1st-April-2021", 14, 0], ["28th-June-2022", 164, 20], ["12th-November-2021", 82, 1], ["7th-June-2021", 29, 0], ["7th-June-2021", 28, 0], ["7th-June-2021", 30, 0], ["14th-November-2022", 38, 4], ["13th-July-2020", 12, 0], ["13th-July-2020", 10, 0], ["27th-June-2020", 338, 1], ["8th-July-2021", 10, 0], ["2nd-April-2021", 69, 11], ["8th-June-2020", 118, 0], ["24th-June-2020", 125, 0], ["24th-June-2020", 272, 0], ["23rd-June-2022", 46, 0], ["23rd-July-2020", 54, 0], ["20th-Augus-2020", 9, 0], ["14th-July-2020", 89, 1], ["14th-July-2020", 90, 0], ["11th-May-2020", 105, 0], ["11th-May-2020", 99, 0], ["11th-May-2020", 69, 0], ["11th-May-2020", 23, 0], ["11th-May-2020", 25, 0], ["1st-October-2021", 56, 16], ["28th-October-2020", 30, 5], ["30th-December-2021", 42, 6], ["30th-December-2021", 42, 8], ["27th-September-2021", 38, 6], ["27th-September-2021", 48, 7], ["27th-September-2021", 36, 5], ["3rd-Augus-2021", 25, 0], ["25th-June-2020", 167, 0], ["25th-June-2020", 168, 0], ["25th-June-2020", 165, 0], ["29th-June-2022", 166, 0], ["11th-May-2022", 33, 3], ["11th-May-2022", 104, 0], ["30th-June-2021", 170, 0], ["24th-July-2020", 45, 0], ["24th-July-2020", 46, 17], ["24th-July-2020", 47, 0], ["6th-Augus-2021", 31, 0], ["6th-Augus-2021", 22, 0], ["6th-Augus-2021", 30, 0], ["22nd-June-2021", 199, 0], ["28th-Marc-2022", 45, 2], ["17th-June-2021", 68, 0], ["29th-January-2021", 73, 12], ["29th-January-2021", 24, 0], ["15th-May-2020", 66, 0], ["15th-May-2020", 84, 0], ["16th-June-2020", 93, 0], ["24th-May-2021", 120, 0], ["24th-May-2021", 115, 0], ["24th-May-2021", 116, 0], ["11th-Augus-2020", 30, 0], ["9th-Augus-2021", 103, 0], ["9th-July-2021", 16, 0], ["9th-July-2021", 7, 0], ["8th-July-2020", 26, 0], ["11th-June-2020", 57, 0], ["14th-September-2020", 60, 13], ["24th-Augus-2020", 7, 0], ["24th-June-2021", 86, 0], ["24th-June-2021", 128, 0], ["24th-June-2021", 128, 0], ["13th-May-2020", 31, 0], ["13th-May-2020", 19, 0], ["25th-Marc-2022", 10, 18], ["25th-Marc-2022", 9, 14], ["23rd-June-2021", 299, 0], ["23rd-June-2021", 162, 0], ["23rd-June-2021", 212, 0], ["23rd-June-2021", 238, 0], ["23rd-June-2021", 233, 0], ["23rd-June-2021", 253, 0]], "nconsign": [["11th-February-1974", 41, 0]], "ncod": [["13th-May-1991", 23, 9]], "ncooksari": [["20th-June-1973", 68, 6]], "ncoairmen": [["8th-September-2003", 12, 35]], "nconsist": [["15th-October-1956", 55, 3]], "ncon": [["7th-Augus-1985", 14, 0]], "ncone": [["22nd-September-2005", 17, 0]], "ncode": [["17th-June-1998", 104, 1]], "ncorrect": [["10th-Marc-1966", 46, 39]]}