{"no140": [["8th-December-1994", 19, 6]], "no146": [["11th-December-1973", 8, 30]], "no156": [["17th-June-2006", 106, 7]], "no159": [["17th-June-2006", 107, 7]], "no164": [["17th-June-2006", 108, 10]], "no12": [["15th-November-2006", 94, 6], ["23rd-June-2013", 92, 26], ["29th-November-2016", 31, 8]], "no13": [["4th-Marc-1948", 50, 11], ["23rd-July-2004", 71, 2]], "no1781": [["24th-June-2010", 102, 8]], "no1782": [["24th-June-2010", 106, 14]], "no1473": [["19th-June-1996", 20, 23]], "no17": [["30th-January-1995", 10, 2]], "no1muslim": [["26th-October-2020", 35, 2]], "no100": [["23rd-Augus-1976", 21, 8]], "no110": [["23rd-Augus-1976", 25, 2]], "no1": [["15th-November-2021", 47, 12], ["19th-June-2006", 107, 1], ["26th-June-2021", 6, 4], ["16th-April-2022", 52, 0], ["11th-November-1986", 102, 0], ["5th-July-1973", 53, 2], ["9th-Augus-2006", 73, 10], ["21st-June-1995", 222, 2], ["21st-June-1974", 3, 8], ["11th-July-2012", 1, 6], ["9th-November-2015", 6, 0], ["18th-June-1989", 87, 21], ["20th-April-2015", 36, 0], ["17th-June-2021", 42, 0], ["10th-Augus-1985", 97, 0], ["15th-Augus-2018", 21, 3], ["25th-June-1996", 50, 0], ["8th-November-1990", 20, 0], ["4th-June-1991", 148, 0], ["4th-May-2006", 66, 9], ["31st-May-2019", 64, 11], ["4th-December-2019", 118, 2], ["24th-June-1995", 150, 22], ["1st-April-2010", 28, 0], ["13th-April-2009", 112, 0]], "no1939": [["22nd-September-1985", 5, 12]], "no11": [["14th-June-2008", 55, 0], ["7th-January-2020", 12, 18], ["24th-December-2008", 73, 24]], "no118": [["8th-October-2009", 57, 25], ["19th-June-2008", 146, 8]], "no144": [["27th-June-1997", 132, 28]], "no173160": [["24th-September-1987", 21, 8]], "no14": [["30th-June-2020", 172, 12]], "no144345": [["7th-November-2018", 71, 19]], "no125": [["29th-June-1998", 8, 2]], "no19": [["16th-Augus-1995", 41, 1]], "no162": [["24th-December-2008", 73, 45]], "no147": [["14th-April-2005", 14, 17]], "no10": [["11th-Augus-2006", 42, 0], ["21st-Augus-1997", 157, 6], ["3rd-Marc-2003", 62, 12]], "no1gi": [["4th-December-1973", 4, 11]], "no166": [["19th-September-2003", 5, 0]], "no1563": [["7th-September-1987", 37, 21]]}