{"ofreport": [["29th-December-2010", 21, 14]], "ofraid": [["16th-October-1996", 69, 5]], "ofrent": [["1st-June-1995", 104, 4]], "ofr": [["21st-Augus-1996", 51, 10], ["14th-Marc-1966", 66, 17], ["24th-February-2005", 70, 21]], "ofreportadopt": [["23rd-December-2010", 49, 4]], "ofriv": [["4th-December-1974", 42, 4], ["29th-October-2018", 51, 3]], "ofrul": [["11th-Augus-1973", 52, 33]], "ofroad": [["19th-January-2018", 60, 2]], "ofrealis": [["11th-October-1950", 94, 2]], "ofreligi": [["2nd-April-1974", 7, 23]], "ofriger": [["17th-February-1992", 32, 16]]}