{"pkwh": [["24th-Augus-1995", 37, 12], ["26th-January-1994", 73, 2], ["26th-January-1994", 72, 6], ["1st-June-1995", 38, 8], ["1st-June-1995", 39, 0], ["1st-June-1995", 39, 9], ["1st-June-1995", 43, 2], ["1st-June-1995", 43, 16], ["1st-June-1995", 44, 0], ["1st-June-1995", 44, 8], ["1st-June-1995", 44, 9], ["13th-May-1996", 29, 5], ["13th-May-1996", 32, 2], ["13th-May-1996", 32, 18], ["13th-May-1996", 33, 0], ["13th-May-1996", 30, 15], ["3rd-June-1991", 7, 2], ["16th-Augus-1995", 58, 0], ["16th-Augus-1995", 56, 1], ["16th-Augus-1995", 55, 11], ["31st-Augus-1994", 21, 1], ["6th-Marc-1998", 60, 0], ["17th-June-1991", 5, 1], ["17th-June-1991", 5, 21], ["17th-June-1991", 5, 24], ["17th-June-1991", 5, 43], ["17th-June-1991", 5, 44]], "pkwi": [["26th-January-1994", 74, 0], ["1st-June-1995", 99, 49], ["16th-Augus-1995", 58, 0], ["16th-Augus-1995", 57, 4], ["16th-Augus-1995", 56, 1]], "pkw": [["26th-January-1994", 73, 3], ["13th-May-1996", 31, 0], ["27th-Augus-1998", 66, 3], ["16th-Augus-1995", 56, 5], ["6th-Marc-1998", 61, 0], ["3rd-January-1973", 29, 13]], "pkwte": [["13th-June-1994", 45, 7]], "pkwid": [["16th-Augus-1995", 57, 4], ["16th-Augus-1995", 55, 11]], "pkwid__": [["16th-Augus-1995", 56, 5]], "pkwhi": [["31st-Augus-1994", 21, 0]]}