{"skud": [["14th-September-1989", 88, 7], ["24th-June-1989", 61, 3]], "skull": [["2nd-February-2012", 5, 2], ["17th-June-2005", 53, 6], ["30th-Marc-1976", 24, 1], ["18th-June-1964", 5, 10], ["21st-June-2006", 76, 0], ["1st-July-1997", 27, 0], ["5th-September-1996", 126, 8], ["25th-September-1953", 105, 11], ["21st-September-1995", 14, 4], ["16th-May-1991", 130, 1], ["26th-November-1973", 52, 5], ["17th-May-2021", 99, 3], ["21st-January-1975", 58, 8], ["9th-Marc-1987", 101, 0], ["18th-June-1963", 37, 1], ["18th-June-1963", 37, 5], ["18th-June-1963", 36, 48], ["5th-January-2016", 62, 0], ["24th-June-1999", 126, 1], ["16th-June-2007", 27, 1], ["9th-May-2005", 133, 0], ["3rd-Augus-2007", 112, 0], ["7th-Augus-1963", 26, 6], ["7th-Augus-1963", 24, 14], ["7th-Augus-1963", 24, 15], ["7th-Augus-1963", 24, 19], ["7th-Augus-1963", 24, 23], ["10th-February-1990", 84, 1], ["24th-December-2008", 130, 0], ["12th-June-1998", 36, 0], ["18th-November-1965", 43, 15], ["14th-October-1985", 88, 5], ["5th-Marc-1987", 9, 2], ["7th-June-1999", 84, 58], ["15th-May-1996", 121, 1], ["15th-May-1996", 122, 0], ["9th-February-1986", 25, 13], ["11th-December-1997", 7, 5], ["8th-May-2014", 45, 0], ["12th-Augus-1985", 139, 2], ["18th-April-2006", 63, 0], ["24th-Marc-2005", 98, 0], ["24th-June-1964", 13, 22], ["27th-June-1974", 62, 22], ["4th-December-1962", 18, 8], ["29th-June-1963", 22, 0], ["6th-May-1968", 19, 17]], "skurst": [["11th-Marc-1991", 91, 24]], "skurdu": [["26th-June-1990", 105, 14], ["14th-December-1986", 61, 76], ["14th-December-1986", 61, 78], ["14th-December-1986", 61, 81], ["14th-December-1986", 61, 82], ["18th-October-1992", 5, 30], ["9th-December-1976", 20, 18], ["24th-June-1998", 172, 8], ["24th-June-1998", 172, 10], ["11th-June-1985", 45, 6]], "sku": [["4th-January-1993", 26, 3], ["4th-Augus-2016", 2, 5]], "skult": [["25th-June-1976", 85, 1]], "skuila": [["5th-December-1973", 32, 8]], "skuk": [["9th-June-2016", 18, 0]], "skuld": [["27th-September-1987", 82, 16]], "skurdunorthern": [["8th-June-1989", 6, 10]], "skuster": [["24th-November-1986", 39, 0]], "skumandar": [["9th-September-1998", 64, 61]], "skusi": [["28th-May-1992", 63, 2], ["31st-October-1995", 22, 0], ["16th-June-2008", 141, 0]], "skul": [["20th-June-1966", 41, 6]], "skunk": [["22nd-April-1957", 62, 9]]}