{"tegriti": [["19th-June-1962", 45, 7], ["28th-Marc-1952", 43, 33], ["3rd-Augus-1965", 3, 14], ["18th-June-1964", 71, 14], ["4th-Marc-1974", 32, 16], ["13th-June-1973", 56, 12], ["27th-June-1968", 16, 24], ["28th-October-1953", 42, 20], ["6th-July-1966", 59, 19], ["10th-July-1965", 72, 20], ["27th-Marc-1963", 58, 12], ["15th-July-1962", 27, 12], ["24th-January-1956", 23, 3], ["13th-April-1963", 42, 25], ["22nd-November-1965", 26, 14], ["3rd-April-1973", 15, 2], ["18th-November-1965", 73, 16], ["25th-May-1963", 13, 0], ["26th-May-1973", 40, 35], ["26th-May-1973", 41, 2], ["12th-Augus-1985", 127, 13], ["24th-June-1964", 108, 18], ["5th-June-1964", 34, 47], ["21st-September-1955", 14, 14], ["28th-May-1968", 87, 3], ["29th-June-1965", 11, 1]], "teg": [["10th-February-1975", 21, 0], ["29th-October-1975", 74, 15], ["14th-February-1993", 69, 18], ["13th-September-1987", 55, 0], ["3rd-Augus-2007", 112, 1], ["21st-October-2005", 82, 3], ["27th-Augus-1997", 74, 47], ["20th-July-2004", 48, 4]], "tegho": [["28th-April-1991", 11, 28], ["19th-June-1996", 81, 9], ["19th-June-1996", 81, 12], ["4th-April-1991", 81, 17]], "tegrat": [["9th-Augus-1973", 8, 0], ["25th-Augus-1955", 4, 36], ["2nd-December-1975", 25, 14], ["19th-April-1952", 5, 12], ["6th-April-1956", 85, 14], ["24th-June-1963", 38, 25], ["15th-December-1966", 19, 28], ["5th-Augus-1963", 10, 33], ["4th-June-1968", 56, 6], ["14th-Marc-1966", 52, 8], ["12th-June-1976", 18, 12], ["29th-June-1967", 69, 8], ["26th-September-1955", 21, 7], ["23rd-February-1957", 4, 22], ["7th-June-1966", 61, 8], ["7th-June-1966", 51, 36], ["17th-May-1948", 15, 35], ["8th-June-1976", 10, 10], ["21st-February-1956", 99, 7]], "tegral": [["15th-Marc-1966", 10, 30], ["12th-July-1972", 65, 7], ["8th-Marc-1958", 75, 18], ["2nd-April-1964", 91, 22]], "tego": [["26th-November-1966", 5, 7], ["27th-June-1973", 75, 13], ["24th-February-2005", 54, 19]], "tegn": [["2nd-December-1985", 53, 3]], "tegani": [["23rd-February-2007", 11, 24]], "tegori": [["1st-February-1987", 77, 28]], "tegeth": [["23rd-April-1957", 44, 10]], "tegobag": [["18th-June-1973", 10, 16]], "tegisl": [["7th-January-2016", 19, 0]], "teguia": [["7th-June-1967", 18, 36]], "tegal": [["5th-December-1973", 41, 18], ["2nd-November-2017", 61, 0]], "tegim": [["26th-February-1989", 43, 20], ["15th-January-1965", 18, 24]], "tegi": [["9th-September-1958", 19, 4], ["26th-June-1965", 85, 3]], "tega": [["7th-December-1973", 30, 5]], "tegeplac": [["6th-May-1992", 44, 11], ["23rd-June-2007", 20, 1]], "tegum": [["21st-June-1995", 18, 96]], "tegra": [["26th-December-2003", 205, 12]], "tegamet2": [["7th-June-1999", 83, 13], ["7th-June-1999", 83, 36], ["7th-June-1999", 85, 71]], "tegament2": [["7th-June-1999", 83, 24]], "tegume2": [["7th-June-1999", 83, 32]], "tegame1": [["7th-June-1999", 86, 5], ["7th-June-1999", 87, 76], ["7th-June-1999", 85, 9], ["7th-June-1999", 85, 12]], "tegner1": [["7th-June-1999", 86, 8]], "tegames1": [["7th-June-1999", 86, 25], ["7th-June-1999", 87, 69]], "tegamer1": [["7th-June-1999", 86, 52], ["7th-June-1999", 85, 64]], "teganes1inj": [["7th-June-1999", 86, 68]], "teget2": [["7th-June-1999", 87, 21]], "tegame2": [["7th-June-1999", 87, 63], ["7th-June-1999", 85, 35]], "tegamer2": [["7th-June-1999", 85, 47], ["7th-June-1999", 84, 22]], "tegames2": [["7th-June-1999", 85, 69], ["7th-June-1999", 85, 75], ["7th-June-1999", 84, 59]], "tegan": [["7th-June-1999", 84, 18]], "tegnet2": [["7th-June-1999", 84, 47]], "tegane1": [["7th-June-1999", 84, 63]], "tegeta": [["14th-October-2004", 44, 9]], "tegular": [["8th-February-2007", 99, 3]], "tegel": [["6th-September-1972", 92, 13]], "teghari": [["19th-February-1991", 87, 14]], "tege": [["8th-June-1967", 36, 2], ["18th-April-1957", 43, 8]], "tegor": [["6th-July-1999", 3, 9]], "tegic": [["19th-Marc-1988", 44, 5], ["24th-May-1967", 63, 14]], "tegent": [["9th-July-1973", 3, 26]], "tegu": [["4th-December-1973", 14, 11]], "tegol": [["25th-Augus-1992", 86, 0]], "tegon": [["19th-January-2009", 40, 5]], "tegroup": [["25th-April-2008", 52, 8], ["25th-April-2008", 52, 14]], "tegard": [["16th-June-1987", 42, 0]], "tegrai": [["5th-September-2005", 56, 9]]}